{"_id":{"$oid":"63dc384df0f223cb74a8dda9"},"questionnaireID":"QQ001","answers":[{"ans":"P01A1","qID":"P01"},{"ans":"Q01A1","qID":"Q01"},{"ans":"Q02A1","qID":"Q02"},{"ans":"Q03A1","qID":"Q03"},{"ans":"Q04A1","qID":"Q04"},{"ans":"Q05A1","qID":"Q05"},{"ans":"Q06A1","qID":"Q06"},{"ans":"Q07A1","qID":"Q07"},{"ans":"Q08A1","qID":"Q08"},{"ans":"Q09A1","qID":"Q09"}],"session":"d4ce"}
{"_id":{"$oid":"63dc3861f0f223cb74a8fb27"},"questionnaireID":"QQ000","answers":[{"ans":"P01A1","qID":"P01"},{"ans":"Q01A1","qID":"Q01"},{"ans":"Q02A1","qID":"Q02"},{"ans":"Q03A1","qID":"Q03"},{"ans":"Q04A1","qID":"Q04"},{"ans":"Q05A1","qID":"Q05"},{"ans":"Q06A1","qID":"Q06"},{"ans":"Q07A1","qID":"Q07"},{"ans":"Q08A1","qID":"Q08"},{"ans":"Q09A2","qID":"Q09"}],"session":"d4te"}
{"_id":{"$oid":"63dd4471efad7ac0e9c3e0d2"},"questionnaireID":"QQ000","answers":[{"ans":"P01A1","qID":"P01"},{"ans":"Q07A2","qID":"Q01"},{"ans":"Q02A1","qID":"Q02"},{"ans":"Q03A1","qID":"Q03"},{"ans":"Q04A1","qID":"Q04"},{"ans":"Q05A1","qID":"Q05"},{"ans":"Q06A1","qID":"Q06"},{"ans":"Q07A1","qID":"Q07"},{"ans":"Q08A1","qID":"Q08"},{"ans":"Q09A2","qID":"Q09"}],"session":"1111"}
{"_id":{"$oid":"63dd5c73a287e99d51abd1ec"},"questionnaireID":"QQ000","answers":[{"ans":"Q01A2","qID":"Q01","_id":{"$oid":"63dd5c73a287e99d51abd1ed"}}],"session":"3333"}
{"_id":{"$oid":"63dd7f3ed43fc677037d7ba9"},"questionnaireID":"QQ000","answers":[{"ans":"P01A1","qID":"P01"},{"ans":"Q01A1","qID":"Q01"},{"ans":"Q02A1","qID":"Q02"},{"ans":"Q03A1","qID":"Q03"},{"ans":"Q04A1","qID":"Q04"},{"ans":"Q05A1","qID":"Q05"},{"ans":"Q06A1","qID":"Q06"},{"ans":"Q07A1","qID":"Q07"},{"ans":"Q08A1","qID":"Q08"},{"ans":"Q09A2","qID":"Q09"}],"session":"2222"}
{"_id":{"$oid":"63e7bd9270a46a907ea002bc"},"questionnaireID":"QQ003","answers":[],"session":"4567"}
{"_id":{"$oid":"63e7bdd370a46a907ea002c3"},"questionnaireID":"QQ003","answers":[{"ans":"Q01A1","qID":"Q01","_id":{"$oid":"63e7bea16b3b6f45bdf20ace"}}],"session":"4568"}
{"_id":{"$oid":"63e7be3970a46a907ea002c8"},"questionnaireID":"QQ003","answers":[{"ans":"Q01A1","qID":"Q01","_id":{"$oid":"63e7be6e9d4ed03357c30f30"}}],"session":"4569"}
{"_id":{"$oid":"63e7beb5eae721e7956bb36f"},"questionnaireID":"QQ003","answers":[],"session":"4599"}
{"_id":{"$oid":"63e7beecba666c0e4c5b74fe"},"questionnaireID":"QQ003","answers":[],"session":"4598"}
{"_id":{"$oid":"63ecf018798b1d88109255ed"},"questionnaireID":"QQ004","answers":[{"ans":"P01A2","qID":"P00","_id":{"$oid":"63ecf018798b1d88109255ee"}},{"ans":"Q01A2","qID":"Q01","_id":{"$oid":"63ecf019798b1d88109255f2"}},{"ans":"Q02A1","qID":"Q02","_id":{"$oid":"63ecf01b798b1d88109255f9"}},{"ans":"Q03A2","qID":"Q03","_id":{"$oid":"63ecf01e798b1d8810925602"}},{"ans":"Q04A2","qID":"Q04","_id":{"$oid":"63ecf020798b1d881092560d"}}],"session":"5803"}
{"_id":{"$oid":"63ecf0bf798b1d88109259a8"},"questionnaireID":"QQ004","answers":[{"ans":"P01A1","qID":"P00","_id":{"$oid":"63ecf0bf798b1d88109259a9"}},{"ans":"Q01A3","qID":"Q01","_id":{"$oid":"63ecf0c4798b1d88109259ad"}},{"ans":"Q02A2","qID":"Q02","_id":{"$oid":"63ecf0c5798b1d88109259b4"}},{"ans":"Q03A3","qID":"Q03","_id":{"$oid":"63ecf0c7798b1d88109259bd"}},{"ans":"Q04A2","qID":"Q04","_id":{"$oid":"63ecf0c9798b1d88109259c8"}}],"session":"4387"}
{"_id":{"$oid":"63ef7ad8852b67ea31425e3e"},"questionnaireID":"QQ002","answers":[{"ans":"P00A2","qID":"P00","_id":{"$oid":"63ef7ad8852b67ea31425e3f"}},{"ans":"P01A1","qID":"P01","_id":{"$oid":"63ef7adb852b67ea31425e43"}},{"ans":"Q01A3","qID":"Q01","_id":{"$oid":"63ef7adf852b67ea31425e4a"}},{"ans":"Q04A2","qID":"Q04","_id":{"$oid":"63ef7af3852b67ea31425e53"}},{"ans":"Q05A1","qID":"Q05","_id":{"$oid":"63ef7af7852b67ea31425e5e"}}],"session":"5388"}
{"_id":{"$oid":"63ef7b52852b67ea314262aa"},"questionnaireID":"QQ002","answers":[{"ans":"P00A1","qID":"P00","_id":{"$oid":"63ef7b52852b67ea314262ab"}},{"ans":"P01A1","qID":"P01","_id":{"$oid":"63ef7b55852b67ea314262af"}},{"ans":"Q01A2","qID":"Q01","_id":{"$oid":"63ef7b57852b67ea314262b6"}},{"ans":"Q03A3","qID":"Q03","_id":{"$oid":"63ef7b5a852b67ea314262bf"}},{"ans":"Q05A2","qID":"Q05","_id":{"$oid":"63ef7b5d852b67ea314262ca"}}],"session":"7887"}
{"_id":{"$oid":"63ef7b77852b67ea314265c2"},"questionnaireID":"QQ002","answers":[{"ans":"P00A1","qID":"P00","_id":{"$oid":"63ef7b77852b67ea314265c3"}},{"ans":"P01A2","qID":"P01","_id":{"$oid":"63ef7b7a852b67ea314265c7"}},{"ans":"Q01A1","qID":"Q01","_id":{"$oid":"63ef7b7c852b67ea314265ce"}},{"ans":"Q02A2","qID":"Q02","_id":{"$oid":"63ef7b7f852b67ea314265d7"}},{"ans":"Q05A1","qID":"Q05","_id":{"$oid":"63ef7b81852b67ea314265e2"}}],"session":"7995"}
{"_id":{"$oid":"63ef7b9c852b67ea314268da"},"questionnaireID":"QQ002","answers":[{"ans":"P00A3","qID":"P00","_id":{"$oid":"63ef7b9c852b67ea314268db"}},{"ans":"P01A4","qID":"P01","_id":{"$oid":"63ef7b9e852b67ea314268df"}},{"ans":"Q01A2","qID":"Q01","_id":{"$oid":"63ef7ba0852b67ea314268e6"}},{"ans":"Q03A3","qID":"Q03","_id":{"$oid":"63ef7ba4852b67ea314268ef"}},{"ans":"Q05A2","qID":"Q05","_id":{"$oid":"63ef7ba6852b67ea314268fa"}}],"session":"3223"}
{"_id":{"$oid":"63ef7be0852b67ea31426cbd"},"questionnaireID":"QQ002","answers":[{"ans":"P00A2","qID":"P00","_id":{"$oid":"63ef7be0852b67ea31426cbe"}},{"ans":"P01A2","qID":"P01","_id":{"$oid":"63ef7be2852b67ea31426cc2"}},{"ans":"Q01A2","qID":"Q01","_id":{"$oid":"63ef7be5852b67ea31426cc9"}},{"ans":"Q03A1","qID":"Q03","_id":{"$oid":"63ef7be9852b67ea31426cd2"}},{"ans":"Q06A1","qID":"Q06","_id":{"$oid":"63ef7bec852b67ea31426cdd"}}],"session":"8103"}
{"_id":{"$oid":"63ef7c38852b67ea31427086"},"questionnaireID":"QQ002","answers":[{"ans":"P00A2","qID":"P00","_id":{"$oid":"63ef7c38852b67ea31427087"}},{"ans":"P01A2","qID":"P01","_id":{"$oid":"63ef7c3a852b67ea3142708b"}},{"ans":"Q01A1","qID":"Q01","_id":{"$oid":"63ef7c3b852b67ea31427092"}},{"ans":"Q02A2","qID":"Q02","_id":{"$oid":"63ef7c3e852b67ea3142709b"}},{"ans":"Q05A1","qID":"Q05","_id":{"$oid":"63ef7c3f852b67ea314270a6"}}],"session":"8224"}
{"_id":{"$oid":"63ef7ff8e4a7f694d236e463"},"questionnaireID":"QQ000","answers":[{"ans":"undefined","qID":"P00","_id":{"$oid":"63ef7ff8e4a7f694d236e464"}}],"session":"2046"}
{"_id":{"$oid":"63ef86789d6cd589c61822c7"},"questionnaireID":"QQ005","answers":[{"ans":"P01A1","qID":"P01","_id":{"$oid":"63ef86789d6cd589c61822c8"}},{"ans":"Q01A2","qID":"Q01","_id":{"$oid":"63ef86799d6cd589c61822cc"}},{"ans":"Q03A1","qID":"Q03","_id":{"$oid":"63ef867a9d6cd589c61822d3"}},{"ans":"Q04A2","qID":"Q04","_id":{"$oid":"63ef867c9d6cd589c61822dc"}}],"session":"1294"}
